{
  "variants":
  { 
    "metal=copper": { "model": "basematerials:blockCopper" },
    "metal=tin": { "model": "basematerials:blockTin" },
    "metal=nickel": { "model": "basematerials:blockNickel" },
    "metal=zinc": { "model": "basematerials:blockZinc" },
    "metal=silver": { "model": "basematerials:blockSilver" },
    "metal=lead": { "model": "basematerials:blockLead" },
    "metal=bronze": { "model": "basematerials:blockBronze" },
    "metal=electrum": { "model": "basematerials:blockElectrum" },
    "metal=invar": { "model": "basematerials:blockInvar" },
    "metal=brass": { "model": "basematerials:blockBrass" },
    "metal=steel": { "model": "basematerials:blockSteel" },
    "metal=platinum": { "model": "basematerials:blockPlatinum" },
    "metal=cupronickel": { "model": "basematerials:blockCupronickel"  },
    "metal=signalum": { "model": "basematerials:blockSignalum"  },
    "metal=lumium": { "model": "basematerials:blockLumium"  }
  }
}

